setup.py
tutorial_package_jeff/__init__.py
tutorial_package_jeff/greet.py
tutorial_package_jeff.egg-info/PKG-INFO
tutorial_package_jeff.egg-info/SOURCES.txt
tutorial_package_jeff.egg-info/dependency_links.txt
tutorial_package_jeff.egg-info/top_level.txt