Metadata-Version: 1.0
Name: tutorial-package-jeff
Version: 0.0.1
Summary: demo package for hands on
Home-page: UNKNOWN
Author: jeffreytang
Author-email: jeffrey.tang@bc.biol.ethz.ch
License: BSD
Platform: UNKNOWN
